rcache2/__init__.py
rcache2-0.0.1.dist-info/LICENSE
rcache2-0.0.1.dist-info/METADATA
rcache2-0.0.1.dist-info/WHEEL
rcache2-0.0.1.dist-info/RECORD
