Metadata-Version: 2.1
Name: rcache2
Version: 0.0.1
Summary: Python redis cache
Home-page: https://github.com/RakhimovRamis/rcache2
License: MIT
Author: Ramis Rakhimov
Author-email: ramisprogramis@gmail.com
Requires-Python: >=3.8,<4.0
Classifier: License :: OSI Approved :: MIT License
Classifier: Programming Language :: Python :: 3
Classifier: Programming Language :: Python :: 3.8
Classifier: Programming Language :: Python :: 3.9
Classifier: Programming Language :: Python :: 3.10
Classifier: Programming Language :: Python :: 3.11
